{
  "lastUpdated": "2026-02-28T17:22:01.594Z",
  "feeds": [
    {
      "blogId": "fromjason",
      "status": "ok",
      "postCount": 25,
      "lastFetched": "2026-02-28T17:20:50.000Z",
      "latencyMs": 367,
      "error": null
    },
    {
      "blogId": "susam",
      "status": "ok",
      "postCount": 20,
      "lastFetched": "2026-02-28T17:20:50.695Z",
      "latencyMs": 1021,
      "error": null
    },
    {
      "blogId": "seangoedecke",
      "status": "ok",
      "postCount": 25,
      "lastFetched": "2026-02-28T17:20:49.930Z",
      "latencyMs": 254,
      "error": null
    },
    {
      "blogId": "ploum",
      "status": "ok",
      "postCount": 10,
      "lastFetched": "2026-02-28T17:20:51.237Z",
      "latencyMs": 1560,
      "error": null
    },
    {
      "blogId": "simonwillison",
      "status": "ok",
      "postCount": 25,
      "lastFetched": "2026-02-28T17:20:50.068Z",
      "latencyMs": 390,
      "error": null
    },
    {
      "blogId": "entropicthoughts",
      "status": "ok",
      "postCount": 25,
      "lastFetched": "2026-02-28T17:20:50.654Z",
      "latencyMs": 975,
      "error": null
    },
    {
      "blogId": "ntietz",
      "status": "ok",
      "postCount": 25,
      "lastFetched": "2026-02-28T17:20:50.896Z",
      "latencyMs": 1217,
      "error": null
    },
    {
      "blogId": "stephango",
      "status": "ok",
      "postCount": 25,
      "lastFetched": "2026-02-28T17:20:50.240Z",
      "latencyMs": 560,
      "error": null
    },
    {
      "blogId": "emilburzo",
      "status": "ok",
      "postCount": 10,
      "lastFetched": "2026-02-28T17:20:50.740Z",
      "latencyMs": 1059,
      "error": null
    },
    {
      "blogId": "alanwsmith",
      "status": "ok",
      "postCount": 16,
      "lastFetched": "2026-02-28T17:20:50.737Z",
      "latencyMs": 1055,
      "error": null
    },
    {
      "blogId": "kudmitry",
      "status": "ok",
      "postCount": 25,
      "lastFetched": "2026-02-28T17:20:51.405Z",
      "latencyMs": 1475,
      "error": null
    },
    {
      "blogId": "seanheelan",
      "status": "ok",
      "postCount": 10,
      "lastFetched": "2026-02-28T17:20:50.610Z",
      "latencyMs": 610,
      "error": null
    },
    {
      "blogId": "gamesbymason",
      "status": "ok",
      "postCount": 25,
      "lastFetched": "2026-02-28T17:20:51.121Z",
      "latencyMs": 1053,
      "error": null
    },
    {
      "blogId": "overreacted",
      "status": "ok",
      "postCount": 25,
      "lastFetched": "2026-02-28T17:20:50.486Z",
      "latencyMs": 245,
      "error": null
    },
    {
      "blogId": "wealthofcommonsense",
      "status": "ok",
      "postCount": 10,
      "lastFetched": "2026-02-28T17:20:51.129Z",
      "latencyMs": 643,
      "error": null
    },
    {
      "blogId": "abnormalreturns",
      "status": "ok",
      "postCount": 14,
      "lastFetched": "2026-02-28T17:20:51.547Z",
      "latencyMs": 937,
      "error": null
    },
    {
      "blogId": "mrkaran",
      "status": "ok",
      "postCount": 25,
      "lastFetched": "2026-02-28T17:20:51.087Z",
      "latencyMs": 433,
      "error": null
    },
    {
      "blogId": "pieterlevels",
      "status": "ok",
      "postCount": 1,
      "lastFetched": "2026-02-28T17:20:50.903Z",
      "latencyMs": 208,
      "error": null
    },
    {
      "blogId": "pluralistic",
      "status": "ok",
      "postCount": 10,
      "lastFetched": "2026-02-28T17:20:52.273Z",
      "latencyMs": 1536,
      "error": null
    },
    {
      "blogId": "sivers",
      "status": "ok",
      "postCount": 25,
      "lastFetched": "2026-02-28T17:20:51.913Z",
      "latencyMs": 1173,
      "error": null
    },
    {
      "blogId": "maggieappleton",
      "status": "ok",
      "postCount": 25,
      "lastFetched": "2026-02-28T17:20:51.196Z",
      "latencyMs": 300,
      "error": null
    },
    {
      "blogId": "marginalian",
      "status": "ok",
      "postCount": 20,
      "lastFetched": "2026-02-28T17:20:51.188Z",
      "latencyMs": 285,
      "error": null
    },
    {
      "blogId": "paulgraham",
      "status": "ok",
      "postCount": 20,
      "lastFetched": "2026-02-28T17:20:51.152Z",
      "latencyMs": 65,
      "error": null
    },
    {
      "blogId": "aldaily",
      "status": "ok",
      "postCount": 10,
      "lastFetched": "2026-02-28T17:20:51.468Z",
      "latencyMs": 347,
      "error": null
    },
    {
      "blogId": "sentiers",
      "status": "ok",
      "postCount": 15,
      "lastFetched": "2026-02-28T17:20:51.431Z",
      "latencyMs": 302,
      "error": null
    },
    {
      "blogId": "benedictevans",
      "status": "ok",
      "postCount": 20,
      "lastFetched": "2026-02-28T17:20:51.639Z",
      "latencyMs": 487,
      "error": null
    },
    {
      "blogId": "nesslabs",
      "status": "ok",
      "postCount": 10,
      "lastFetched": "2026-02-28T17:20:51.472Z",
      "latencyMs": 284,
      "error": null
    },
    {
      "blogId": "slackwire",
      "status": "ok",
      "postCount": 10,
      "lastFetched": "2026-02-28T17:20:51.587Z",
      "latencyMs": 391,
      "error": null
    },
    {
      "blogId": "marginalrevolution",
      "status": "ok",
      "postCount": 15,
      "lastFetched": "2026-02-28T17:20:51.535Z",
      "latencyMs": 298,
      "error": null
    },
    {
      "blogId": "interconnects",
      "status": "ok",
      "postCount": 20,
      "lastFetched": "2026-02-28T17:20:51.788Z",
      "latencyMs": 383,
      "error": null
    },
    {
      "blogId": "markcarrigan",
      "status": "ok",
      "postCount": 10,
      "lastFetched": "2026-02-28T17:20:51.656Z",
      "latencyMs": 225,
      "error": null
    },
    {
      "blogId": "lucumr",
      "status": "ok",
      "postCount": 10,
      "lastFetched": "2026-02-28T17:20:51.793Z",
      "latencyMs": 325,
      "error": null
    },
    {
      "blogId": "kottke",
      "status": "ok",
      "postCount": 25,
      "lastFetched": "2026-02-28T17:20:51.953Z",
      "latencyMs": 481,
      "error": null
    },
    {
      "blogId": "shreevatsa",
      "status": "ok",
      "postCount": 25,
      "lastFetched": "2026-02-28T17:20:52.037Z",
      "latencyMs": 502,
      "error": null
    },
    {
      "blogId": "lukeburgis",
      "status": "ok",
      "postCount": 20,
      "lastFetched": "2026-02-28T17:20:51.934Z",
      "latencyMs": 387,
      "error": null
    },
    {
      "blogId": "commonreader",
      "status": "ok",
      "postCount": 20,
      "lastFetched": "2026-02-28T17:20:51.888Z",
      "latencyMs": 301,
      "error": null
    },
    {
      "blogId": "programmablemutter",
      "status": "ok",
      "postCount": 20,
      "lastFetched": "2026-02-28T17:20:52.149Z",
      "latencyMs": 510,
      "error": null
    },
    {
      "blogId": "venkateshrao",
      "status": "ok",
      "postCount": 20,
      "lastFetched": "2026-02-28T17:20:51.998Z",
      "latencyMs": 342,
      "error": null
    },
    {
      "blogId": "millersbookreview",
      "status": "ok",
      "postCount": 20,
      "lastFetched": "2026-02-28T17:20:52.061Z",
      "latencyMs": 273,
      "error": null
    },
    {
      "blogId": "strangeloopcanon",
      "status": "ok",
      "postCount": 20,
      "lastFetched": "2026-02-28T17:20:52.161Z",
      "latencyMs": 368,
      "error": null
    },
    {
      "blogId": "collabfund",
      "status": "ok",
      "postCount": 12,
      "lastFetched": "2026-02-28T17:20:52.254Z",
      "latencyMs": 365,
      "error": null
    },
    {
      "blogId": "hyperdimensional",
      "status": "ok",
      "postCount": 20,
      "lastFetched": "2026-02-28T17:20:52.372Z",
      "latencyMs": 459,
      "error": null
    },
    {
      "blogId": "astralcodexten",
      "status": "ok",
      "postCount": 20,
      "lastFetched": "2026-02-28T17:20:52.364Z",
      "latencyMs": 430,
      "error": null
    },
    {
      "blogId": "plainenglish",
      "status": "ok",
      "postCount": 20,
      "lastFetched": "2026-02-28T17:20:52.487Z",
      "latencyMs": 534,
      "error": null
    },
    {
      "blogId": "noahpinion",
      "status": "ok",
      "postCount": 20,
      "lastFetched": "2026-02-28T17:20:52.458Z",
      "latencyMs": 460,
      "error": null
    },
    {
      "blogId": "understandingai",
      "status": "ok",
      "postCount": 20,
      "lastFetched": "2026-02-28T17:20:52.415Z",
      "latencyMs": 378,
      "error": null
    },
    {
      "blogId": "highcapacity",
      "status": "error",
      "postCount": 0,
      "lastFetched": "2026-02-28T17:20:53.361Z",
      "latencyMs": 1300,
      "error": "Invalid character in entity name\nLine: 172\nColumn: 97\nChar: ="
    },
    {
      "blogId": "grumpyeconomist",
      "status": "ok",
      "postCount": 20,
      "lastFetched": "2026-02-28T17:20:52.648Z",
      "latencyMs": 499,
      "error": null
    },
    {
      "blogId": "oneusefulthing",
      "status": "ok",
      "postCount": 20,
      "lastFetched": "2026-02-28T17:20:52.549Z",
      "latencyMs": 388,
      "error": null
    },
    {
      "blogId": "defaultblog",
      "status": "ok",
      "postCount": 20,
      "lastFetched": "2026-02-28T17:20:52.786Z",
      "latencyMs": 531,
      "error": null
    },
    {
      "blogId": "onmyom",
      "status": "ok",
      "postCount": 3,
      "lastFetched": "2026-02-28T17:20:52.511Z",
      "latencyMs": 238,
      "error": null
    },
    {
      "blogId": "ofdollarsanddata",
      "status": "ok",
      "postCount": 10,
      "lastFetched": "2026-02-28T17:20:53.099Z",
      "latencyMs": 735,
      "error": null
    },
    {
      "blogId": "flowingdata",
      "status": "ok",
      "postCount": 10,
      "lastFetched": "2026-02-28T17:20:52.607Z",
      "latencyMs": 235,
      "error": null
    },
    {
      "blogId": "anildash",
      "status": "ok",
      "postCount": 12,
      "lastFetched": "2026-02-28T17:20:52.750Z",
      "latencyMs": 335,
      "error": null
    },
    {
      "blogId": "spyglass",
      "status": "ok",
      "postCount": 15,
      "lastFetched": "2026-02-28T17:20:53.334Z",
      "latencyMs": 876,
      "error": null
    },
    {
      "blogId": "honestbroker",
      "status": "ok",
      "postCount": 20,
      "lastFetched": "2026-02-28T17:20:52.839Z",
      "latencyMs": 350,
      "error": null
    },
    {
      "blogId": "wisdomofcrowds",
      "status": "ok",
      "postCount": 20,
      "lastFetched": "2026-02-28T17:20:52.954Z",
      "latencyMs": 443,
      "error": null
    },
    {
      "blogId": "bloodinthemachine",
      "status": "ok",
      "postCount": 20,
      "lastFetched": "2026-02-28T17:20:53.014Z",
      "latencyMs": 465,
      "error": null
    },
    {
      "blogId": "smallpotatoes",
      "status": "ok",
      "postCount": 20,
      "lastFetched": "2026-02-28T17:20:53.164Z",
      "latencyMs": 557,
      "error": null
    },
    {
      "blogId": "ageofinvention",
      "status": "ok",
      "postCount": 20,
      "lastFetched": "2026-02-28T17:20:53.130Z",
      "latencyMs": 482,
      "error": null
    },
    {
      "blogId": "optimallyirrational",
      "status": "ok",
      "postCount": 20,
      "lastFetched": "2026-02-28T17:20:53.238Z",
      "latencyMs": 488,
      "error": null
    },
    {
      "blogId": "conspicuouscognition",
      "status": "ok",
      "postCount": 20,
      "lastFetched": "2026-02-28T17:20:53.295Z",
      "latencyMs": 509,
      "error": null
    },
    {
      "blogId": "speakandregret",
      "status": "ok",
      "postCount": 20,
      "lastFetched": "2026-02-28T17:20:53.467Z",
      "latencyMs": 628,
      "error": null
    },
    {
      "blogId": "experimentalhistory",
      "status": "ok",
      "postCount": 20,
      "lastFetched": "2026-02-28T17:20:53.312Z",
      "latencyMs": 358,
      "error": null
    },
    {
      "blogId": "intrinsicperspective",
      "status": "ok",
      "postCount": 20,
      "lastFetched": "2026-02-28T17:20:53.433Z",
      "latencyMs": 419,
      "error": null
    },
    {
      "blogId": "everythingisbullshit",
      "status": "ok",
      "postCount": 20,
      "lastFetched": "2026-02-28T17:20:53.492Z",
      "latencyMs": 393,
      "error": null
    },
    {
      "blogId": "henrikkarlsson",
      "status": "ok",
      "postCount": 20,
      "lastFetched": "2026-02-28T17:20:53.481Z",
      "latencyMs": 351,
      "error": null
    },
    {
      "blogId": "aiascendant",
      "status": "ok",
      "postCount": 20,
      "lastFetched": "2026-02-28T17:20:53.505Z",
      "latencyMs": 341,
      "error": null
    },
    {
      "blogId": "danq",
      "status": "ok",
      "postCount": 25,
      "lastFetched": "2026-02-28T17:20:55.142Z",
      "latencyMs": 1904,
      "error": null
    },
    {
      "blogId": "mertbulan",
      "status": "ok",
      "postCount": 10,
      "lastFetched": "2026-02-28T17:20:53.513Z",
      "latencyMs": 218,
      "error": null
    },
    {
      "blogId": "tautvilas",
      "status": "ok",
      "postCount": 10,
      "lastFetched": "2026-02-28T17:20:53.673Z",
      "latencyMs": 361,
      "error": null
    },
    {
      "blogId": "oliverhartwich",
      "status": "ok",
      "postCount": 25,
      "lastFetched": "2026-02-28T17:20:53.447Z",
      "latencyMs": 113,
      "error": null
    },
    {
      "blogId": "miketech",
      "status": "ok",
      "postCount": 1,
      "lastFetched": "2026-02-28T17:20:53.519Z",
      "latencyMs": 158,
      "error": null
    },
    {
      "blogId": "platformer",
      "status": "ok",
      "postCount": 15,
      "lastFetched": "2026-02-28T17:20:53.604Z",
      "latencyMs": 171,
      "error": null
    },
    {
      "blogId": "scattershot",
      "status": "ok",
      "postCount": 25,
      "lastFetched": "2026-02-28T17:20:53.772Z",
      "latencyMs": 325,
      "error": null
    },
    {
      "blogId": "nadh",
      "status": "ok",
      "postCount": 18,
      "lastFetched": "2026-02-28T17:20:56.488Z",
      "latencyMs": 3021,
      "error": null
    },
    {
      "blogId": "tessellatum",
      "status": "ok",
      "postCount": 10,
      "lastFetched": "2026-02-28T17:20:53.734Z",
      "latencyMs": 253,
      "error": null
    },
    {
      "blogId": "mostlyeconomics",
      "status": "ok",
      "postCount": 10,
      "lastFetched": "2026-02-28T17:20:53.590Z",
      "latencyMs": 98,
      "error": null
    },
    {
      "blogId": "matt",
      "status": "ok",
      "postCount": 25,
      "lastFetched": "2026-02-28T17:20:54.132Z",
      "latencyMs": 627,
      "error": null
    },
    {
      "blogId": "mrzepczynski",
      "status": "ok",
      "postCount": 25,
      "lastFetched": "2026-02-28T17:20:53.951Z",
      "latencyMs": 438,
      "error": null
    },
    {
      "blogId": "damodaran",
      "status": "ok",
      "postCount": 25,
      "lastFetched": "2026-02-28T17:20:54.037Z",
      "latencyMs": 518,
      "error": null
    },
    {
      "blogId": "ritholtz",
      "status": "ok",
      "postCount": 10,
      "lastFetched": "2026-02-28T17:20:53.981Z",
      "latencyMs": 391,
      "error": null
    },
    {
      "blogId": "danshapiro",
      "status": "ok",
      "postCount": 10,
      "lastFetched": "2026-02-28T17:20:57.511Z",
      "latencyMs": 3907,
      "error": null
    },
    {
      "blogId": "surfingcomplexity",
      "status": "ok",
      "postCount": 10,
      "lastFetched": "2026-02-28T17:20:53.922Z",
      "latencyMs": 248,
      "error": null
    },
    {
      "blogId": "jamesdrandall",
      "status": "ok",
      "postCount": 25,
      "lastFetched": "2026-02-28T17:20:54.346Z",
      "latencyMs": 612,
      "error": null
    },
    {
      "blogId": "teendifferent",
      "status": "ok",
      "postCount": 7,
      "lastFetched": "2026-02-28T17:20:57.697Z",
      "latencyMs": 186,
      "error": null
    },
    {
      "blogId": "thezvi",
      "status": "ok",
      "postCount": 20,
      "lastFetched": "2026-02-28T17:20:57.734Z",
      "latencyMs": 221,
      "error": null
    },
    {
      "blogId": "hollisrobbins",
      "status": "ok",
      "postCount": 20,
      "lastFetched": "2026-02-28T17:20:57.755Z",
      "latencyMs": 241,
      "error": null
    },
    {
      "blogId": "freddiedeboer",
      "status": "ok",
      "postCount": 20,
      "lastFetched": "2026-02-28T17:20:57.676Z",
      "latencyMs": 160,
      "error": null
    },
    {
      "blogId": "onepercentrule",
      "status": "ok",
      "postCount": 20,
      "lastFetched": "2026-02-28T17:21:03.037Z",
      "latencyMs": 282,
      "error": null
    },
    {
      "blogId": "maxread",
      "status": "ok",
      "postCount": 20,
      "lastFetched": "2026-02-28T17:21:02.905Z",
      "latencyMs": 147,
      "error": null
    },
    {
      "blogId": "summerlightning",
      "status": "ok",
      "postCount": 20,
      "lastFetched": "2026-02-28T17:21:02.867Z",
      "latencyMs": 108,
      "error": null
    },
    {
      "blogId": "ghostsofelectricity",
      "status": "ok",
      "postCount": 11,
      "lastFetched": "2026-02-28T17:21:03.022Z",
      "latencyMs": 262,
      "error": null
    },
    {
      "blogId": "kneelingbus",
      "status": "ok",
      "postCount": 20,
      "lastFetched": "2026-02-28T17:21:08.138Z",
      "latencyMs": 99,
      "error": null
    },
    {
      "blogId": "thecuttingfloor",
      "status": "ok",
      "postCount": 20,
      "lastFetched": "2026-02-28T17:21:08.261Z",
      "latencyMs": 220,
      "error": null
    },
    {
      "blogId": "paulkrugman",
      "status": "ok",
      "postCount": 20,
      "lastFetched": "2026-02-28T17:21:08.152Z",
      "latencyMs": 110,
      "error": null
    },
    {
      "blogId": "arpitrage",
      "status": "ok",
      "postCount": 20,
      "lastFetched": "2026-02-28T17:21:08.279Z",
      "latencyMs": 236,
      "error": null
    },
    {
      "blogId": "kyla",
      "status": "ok",
      "postCount": 20,
      "lastFetched": "2026-02-28T17:21:13.444Z",
      "latencyMs": 163,
      "error": null
    },
    {
      "blogId": "larryswedroe",
      "status": "ok",
      "postCount": 20,
      "lastFetched": "2026-02-28T17:21:13.410Z",
      "latencyMs": 128,
      "error": null
    },
    {
      "blogId": "klementoninvesting",
      "status": "ok",
      "postCount": 20,
      "lastFetched": "2026-02-28T17:21:13.461Z",
      "latencyMs": 178,
      "error": null
    },
    {
      "blogId": "downtownjoshbrown",
      "status": "ok",
      "postCount": 3,
      "lastFetched": "2026-02-28T17:21:13.598Z",
      "latencyMs": 314,
      "error": null
    },
    {
      "blogId": "betterletter",
      "status": "ok",
      "postCount": 20,
      "lastFetched": "2026-02-28T17:21:18.767Z",
      "latencyMs": 169,
      "error": null
    },
    {
      "blogId": "overthefield",
      "status": "ok",
      "postCount": 20,
      "lastFetched": "2026-02-28T17:21:18.793Z",
      "latencyMs": 193,
      "error": null
    },
    {
      "blogId": "pilgrimsinthemachine",
      "status": "ok",
      "postCount": 20,
      "lastFetched": "2026-02-28T17:21:18.783Z",
      "latencyMs": 181,
      "error": null
    },
    {
      "blogId": "convivialsociety",
      "status": "ok",
      "postCount": 20,
      "lastFetched": "2026-02-28T17:21:18.714Z",
      "latencyMs": 111,
      "error": null
    },
    {
      "blogId": "stockviz",
      "status": "ok",
      "postCount": 20,
      "lastFetched": "2026-02-28T17:21:23.944Z",
      "latencyMs": 151,
      "error": null
    },
    {
      "blogId": "openquestions",
      "status": "ok",
      "postCount": 20,
      "lastFetched": "2026-02-28T17:21:24.009Z",
      "latencyMs": 214,
      "error": null
    },
    {
      "blogId": "wollenblog",
      "status": "ok",
      "postCount": 20,
      "lastFetched": "2026-02-28T17:21:23.974Z",
      "latencyMs": 178,
      "error": null
    },
    {
      "blogId": "koenfucius",
      "status": "ok",
      "postCount": 20,
      "lastFetched": "2026-02-28T17:21:23.996Z",
      "latencyMs": 198,
      "error": null
    },
    {
      "blogId": "benthamsbulldog",
      "status": "ok",
      "postCount": 20,
      "lastFetched": "2026-02-28T17:21:29.162Z",
      "latencyMs": 151,
      "error": null
    },
    {
      "blogId": "curtjaimungal",
      "status": "ok",
      "postCount": 20,
      "lastFetched": "2026-02-28T17:21:29.223Z",
      "latencyMs": 210,
      "error": null
    },
    {
      "blogId": "nicholasgruen",
      "status": "ok",
      "postCount": 20,
      "lastFetched": "2026-02-28T17:21:29.495Z",
      "latencyMs": 479,
      "error": null
    },
    {
      "blogId": "atmoio",
      "status": "ok",
      "postCount": 4,
      "lastFetched": "2026-02-28T17:21:29.208Z",
      "latencyMs": 192,
      "error": null
    },
    {
      "blogId": "pertinentobservations",
      "status": "ok",
      "postCount": 20,
      "lastFetched": "2026-02-28T17:21:34.693Z",
      "latencyMs": 197,
      "error": null
    },
    {
      "blogId": "nevermetascience",
      "status": "ok",
      "postCount": 20,
      "lastFetched": "2026-02-28T17:21:34.707Z",
      "latencyMs": 210,
      "error": null
    },
    {
      "blogId": "personalcanon",
      "status": "ok",
      "postCount": 20,
      "lastFetched": "2026-02-28T17:21:34.809Z",
      "latencyMs": 311,
      "error": null
    },
    {
      "blogId": "cosmographia",
      "status": "ok",
      "postCount": 20,
      "lastFetched": "2026-02-28T17:21:34.596Z",
      "latencyMs": 97,
      "error": null
    },
    {
      "blogId": "nadig",
      "status": "ok",
      "postCount": 20,
      "lastFetched": "2026-02-28T17:21:40.000Z",
      "latencyMs": 189,
      "error": null
    },
    {
      "blogId": "thechoiceengine",
      "status": "ok",
      "postCount": 9,
      "lastFetched": "2026-02-28T17:21:40.125Z",
      "latencyMs": 312,
      "error": null
    },
    {
      "blogId": "braddelong",
      "status": "ok",
      "postCount": 20,
      "lastFetched": "2026-02-28T17:21:39.954Z",
      "latencyMs": 140,
      "error": null
    },
    {
      "blogId": "branko",
      "status": "ok",
      "postCount": 20,
      "lastFetched": "2026-02-28T17:21:40.036Z",
      "latencyMs": 221,
      "error": null
    },
    {
      "blogId": "bignewsletter",
      "status": "ok",
      "postCount": 20,
      "lastFetched": "2026-02-28T17:21:45.269Z",
      "latencyMs": 142,
      "error": null
    },
    {
      "blogId": "economicforces",
      "status": "ok",
      "postCount": 20,
      "lastFetched": "2026-02-28T17:21:45.352Z",
      "latencyMs": 223,
      "error": null
    },
    {
      "blogId": "thebasecamp",
      "status": "ok",
      "postCount": 20,
      "lastFetched": "2026-02-28T17:21:45.374Z",
      "latencyMs": 244,
      "error": null
    },
    {
      "blogId": "worksonmymachine",
      "status": "ok",
      "postCount": 20,
      "lastFetched": "2026-02-28T17:21:45.239Z",
      "latencyMs": 108,
      "error": null
    },
    {
      "blogId": "cleareyedai",
      "status": "ok",
      "postCount": 20,
      "lastFetched": "2026-02-28T17:21:50.753Z",
      "latencyMs": 379,
      "error": null
    },
    {
      "blogId": "davidoks",
      "status": "ok",
      "postCount": 15,
      "lastFetched": "2026-02-28T17:21:50.581Z",
      "latencyMs": 205,
      "error": null
    },
    {
      "blogId": "robhenderson",
      "status": "ok",
      "postCount": 20,
      "lastFetched": "2026-02-28T17:21:50.486Z",
      "latencyMs": 109,
      "error": null
    },
    {
      "blogId": "andymasley",
      "status": "ok",
      "postCount": 20,
      "lastFetched": "2026-02-28T17:21:50.609Z",
      "latencyMs": 231,
      "error": null
    },
    {
      "blogId": "helentoner",
      "status": "ok",
      "postCount": 9,
      "lastFetched": "2026-02-28T17:21:55.934Z",
      "latencyMs": 179,
      "error": null
    },
    {
      "blogId": "persuasion",
      "status": "ok",
      "postCount": 20,
      "lastFetched": "2026-02-28T17:21:56.167Z",
      "latencyMs": 411,
      "error": null
    },
    {
      "blogId": "afterbabel",
      "status": "ok",
      "postCount": 20,
      "lastFetched": "2026-02-28T17:21:55.876Z",
      "latencyMs": 119,
      "error": null
    },
    {
      "blogId": "importai",
      "status": "ok",
      "postCount": 20,
      "lastFetched": "2026-02-28T17:21:55.986Z",
      "latencyMs": 227,
      "error": null
    },
    {
      "blogId": "byfire",
      "status": "ok",
      "postCount": 11,
      "lastFetched": "2026-02-28T17:22:01.555Z",
      "latencyMs": 388,
      "error": null
    },
    {
      "blogId": "investmentecosystem",
      "status": "ok",
      "postCount": 5,
      "lastFetched": "2026-02-28T17:22:01.339Z",
      "latencyMs": 170,
      "error": null
    },
    {
      "blogId": "weltinnenpolitik",
      "status": "ok",
      "postCount": 14,
      "lastFetched": "2026-02-28T17:22:01.400Z",
      "latencyMs": 229,
      "error": null
    }
  ],
  "summary": {
    "total": 136,
    "healthy": 135,
    "errors": 1
  }
}