{
  "lastUpdated": "2026-03-22T03:35:38.564Z",
  "feeds": [
    {
      "blogId": "fromjason",
      "status": "ok",
      "postCount": 25,
      "lastFetched": "2026-03-22T03:34:30.209Z",
      "latencyMs": 30178,
      "error": null
    },
    {
      "blogId": "susam",
      "status": "ok",
      "postCount": 20,
      "lastFetched": "2026-03-22T03:34:00.738Z",
      "latencyMs": 668,
      "error": null
    },
    {
      "blogId": "seangoedecke",
      "status": "ok",
      "postCount": 25,
      "lastFetched": "2026-03-22T03:34:00.278Z",
      "latencyMs": 207,
      "error": null
    },
    {
      "blogId": "ploum",
      "status": "ok",
      "postCount": 10,
      "lastFetched": "2026-03-22T03:34:01.234Z",
      "latencyMs": 1162,
      "error": null
    },
    {
      "blogId": "simonwillison",
      "status": "ok",
      "postCount": 25,
      "lastFetched": "2026-03-22T03:34:00.336Z",
      "latencyMs": 263,
      "error": null
    },
    {
      "blogId": "entropicthoughts",
      "status": "ok",
      "postCount": 25,
      "lastFetched": "2026-03-22T03:34:00.865Z",
      "latencyMs": 791,
      "error": null
    },
    {
      "blogId": "ntietz",
      "status": "ok",
      "postCount": 25,
      "lastFetched": "2026-03-22T03:34:00.620Z",
      "latencyMs": 546,
      "error": null
    },
    {
      "blogId": "stephango",
      "status": "ok",
      "postCount": 25,
      "lastFetched": "2026-03-22T03:34:00.635Z",
      "latencyMs": 560,
      "error": null
    },
    {
      "blogId": "emilburzo",
      "status": "ok",
      "postCount": 10,
      "lastFetched": "2026-03-22T03:34:01.146Z",
      "latencyMs": 1070,
      "error": null
    },
    {
      "blogId": "alanwsmith",
      "status": "ok",
      "postCount": 12,
      "lastFetched": "2026-03-22T03:34:00.771Z",
      "latencyMs": 694,
      "error": null
    },
    {
      "blogId": "kudmitry",
      "status": "ok",
      "postCount": 25,
      "lastFetched": "2026-03-22T03:34:01.577Z",
      "latencyMs": 1299,
      "error": null
    },
    {
      "blogId": "seanheelan",
      "status": "ok",
      "postCount": 10,
      "lastFetched": "2026-03-22T03:34:00.716Z",
      "latencyMs": 380,
      "error": null
    },
    {
      "blogId": "gamesbymason",
      "status": "ok",
      "postCount": 25,
      "lastFetched": "2026-03-22T03:34:01.165Z",
      "latencyMs": 545,
      "error": null
    },
    {
      "blogId": "overreacted",
      "status": "ok",
      "postCount": 25,
      "lastFetched": "2026-03-22T03:34:00.725Z",
      "latencyMs": 90,
      "error": null
    },
    {
      "blogId": "wealthofcommonsense",
      "status": "ok",
      "postCount": 10,
      "lastFetched": "2026-03-22T03:34:00.911Z",
      "latencyMs": 195,
      "error": null
    },
    {
      "blogId": "abnormalreturns",
      "status": "ok",
      "postCount": 14,
      "lastFetched": "2026-03-22T03:34:00.977Z",
      "latencyMs": 252,
      "error": null
    },
    {
      "blogId": "mrkaran",
      "status": "ok",
      "postCount": 25,
      "lastFetched": "2026-03-22T03:34:01.143Z",
      "latencyMs": 405,
      "error": null
    },
    {
      "blogId": "pieterlevels",
      "status": "ok",
      "postCount": 1,
      "lastFetched": "2026-03-22T03:34:00.944Z",
      "latencyMs": 173,
      "error": null
    },
    {
      "blogId": "pluralistic",
      "status": "ok",
      "postCount": 10,
      "lastFetched": "2026-03-22T03:34:01.898Z",
      "latencyMs": 1033,
      "error": null
    },
    {
      "blogId": "sivers",
      "status": "ok",
      "postCount": 25,
      "lastFetched": "2026-03-22T03:34:01.376Z",
      "latencyMs": 465,
      "error": null
    },
    {
      "blogId": "maggieappleton",
      "status": "ok",
      "postCount": 25,
      "lastFetched": "2026-03-22T03:34:01.201Z",
      "latencyMs": 257,
      "error": null
    },
    {
      "blogId": "marginalian",
      "status": "ok",
      "postCount": 20,
      "lastFetched": "2026-03-22T03:34:01.471Z",
      "latencyMs": 493,
      "error": null
    },
    {
      "blogId": "paulgraham",
      "status": "ok",
      "postCount": 20,
      "lastFetched": "2026-03-22T03:34:01.256Z",
      "latencyMs": 113,
      "error": null
    },
    {
      "blogId": "aldaily",
      "status": "ok",
      "postCount": 10,
      "lastFetched": "2026-03-22T03:34:01.311Z",
      "latencyMs": 164,
      "error": null
    },
    {
      "blogId": "sentiers",
      "status": "ok",
      "postCount": 15,
      "lastFetched": "2026-03-22T03:34:01.511Z",
      "latencyMs": 346,
      "error": null
    },
    {
      "blogId": "benedictevans",
      "status": "ok",
      "postCount": 20,
      "lastFetched": "2026-03-22T03:34:01.611Z",
      "latencyMs": 410,
      "error": null
    },
    {
      "blogId": "nesslabs",
      "status": "ok",
      "postCount": 10,
      "lastFetched": "2026-03-22T03:34:01.825Z",
      "latencyMs": 591,
      "error": null
    },
    {
      "blogId": "slackwire",
      "status": "ok",
      "postCount": 10,
      "lastFetched": "2026-03-22T03:34:02.244Z",
      "latencyMs": 988,
      "error": null
    },
    {
      "blogId": "marginalrevolution",
      "status": "ok",
      "postCount": 15,
      "lastFetched": "2026-03-22T03:34:01.766Z",
      "latencyMs": 455,
      "error": null
    },
    {
      "blogId": "interconnects",
      "status": "ok",
      "postCount": 20,
      "lastFetched": "2026-03-22T03:34:01.860Z",
      "latencyMs": 484,
      "error": null
    },
    {
      "blogId": "markcarrigan",
      "status": "ok",
      "postCount": 10,
      "lastFetched": "2026-03-22T03:34:01.641Z",
      "latencyMs": 170,
      "error": null
    },
    {
      "blogId": "lucumr",
      "status": "ok",
      "postCount": 10,
      "lastFetched": "2026-03-22T03:34:01.804Z",
      "latencyMs": 293,
      "error": null
    },
    {
      "blogId": "kottke",
      "status": "ok",
      "postCount": 25,
      "lastFetched": "2026-03-22T03:34:01.819Z",
      "latencyMs": 242,
      "error": null
    },
    {
      "blogId": "shreevatsa",
      "status": "ok",
      "postCount": 25,
      "lastFetched": "2026-03-22T03:34:02.089Z",
      "latencyMs": 478,
      "error": null
    },
    {
      "blogId": "lukeburgis",
      "status": "ok",
      "postCount": 20,
      "lastFetched": "2026-03-22T03:34:01.977Z",
      "latencyMs": 336,
      "error": null
    },
    {
      "blogId": "commonreader",
      "status": "ok",
      "postCount": 20,
      "lastFetched": "2026-03-22T03:34:01.966Z",
      "latencyMs": 200,
      "error": null
    },
    {
      "blogId": "programmablemutter",
      "status": "ok",
      "postCount": 20,
      "lastFetched": "2026-03-22T03:34:02.279Z",
      "latencyMs": 475,
      "error": null
    },
    {
      "blogId": "venkateshrao",
      "status": "ok",
      "postCount": 20,
      "lastFetched": "2026-03-22T03:34:02.051Z",
      "latencyMs": 232,
      "error": null
    },
    {
      "blogId": "millersbookreview",
      "status": "ok",
      "postCount": 20,
      "lastFetched": "2026-03-22T03:34:02.200Z",
      "latencyMs": 375,
      "error": null
    },
    {
      "blogId": "strangeloopcanon",
      "status": "ok",
      "postCount": 20,
      "lastFetched": "2026-03-22T03:34:02.294Z",
      "latencyMs": 433,
      "error": null
    },
    {
      "blogId": "collabfund",
      "status": "ok",
      "postCount": 12,
      "lastFetched": "2026-03-22T03:34:02.378Z",
      "latencyMs": 480,
      "error": null
    },
    {
      "blogId": "hyperdimensional",
      "status": "ok",
      "postCount": 20,
      "lastFetched": "2026-03-22T03:34:02.321Z",
      "latencyMs": 355,
      "error": null
    },
    {
      "blogId": "astralcodexten",
      "status": "ok",
      "postCount": 20,
      "lastFetched": "2026-03-22T03:34:02.372Z",
      "latencyMs": 395,
      "error": null
    },
    {
      "blogId": "plainenglish",
      "status": "ok",
      "postCount": 20,
      "lastFetched": "2026-03-22T03:34:02.572Z",
      "latencyMs": 521,
      "error": null
    },
    {
      "blogId": "noahpinion",
      "status": "ok",
      "postCount": 20,
      "lastFetched": "2026-03-22T03:34:02.427Z",
      "latencyMs": 338,
      "error": null
    },
    {
      "blogId": "understandingai",
      "status": "ok",
      "postCount": 20,
      "lastFetched": "2026-03-22T03:34:02.582Z",
      "latencyMs": 382,
      "error": null
    },
    {
      "blogId": "highcapacity",
      "status": "error",
      "postCount": 0,
      "lastFetched": "2026-03-22T03:34:03.446Z",
      "latencyMs": 1201,
      "error": "Invalid character in entity name\nLine: 170\nColumn: 97\nChar: ="
    },
    {
      "blogId": "grumpyeconomist",
      "status": "ok",
      "postCount": 20,
      "lastFetched": "2026-03-22T03:34:02.654Z",
      "latencyMs": 375,
      "error": null
    },
    {
      "blogId": "oneusefulthing",
      "status": "ok",
      "postCount": 20,
      "lastFetched": "2026-03-22T03:34:02.797Z",
      "latencyMs": 503,
      "error": null
    },
    {
      "blogId": "defaultblog",
      "status": "ok",
      "postCount": 20,
      "lastFetched": "2026-03-22T03:34:02.716Z",
      "latencyMs": 395,
      "error": null
    },
    {
      "blogId": "onmyom",
      "status": "ok",
      "postCount": 3,
      "lastFetched": "2026-03-22T03:34:02.684Z",
      "latencyMs": 312,
      "error": null
    },
    {
      "blogId": "ofdollarsanddata",
      "status": "ok",
      "postCount": 10,
      "lastFetched": "2026-03-22T03:34:03.299Z",
      "latencyMs": 921,
      "error": null
    },
    {
      "blogId": "flowingdata",
      "status": "ok",
      "postCount": 10,
      "lastFetched": "2026-03-22T03:34:02.924Z",
      "latencyMs": 497,
      "error": null
    },
    {
      "blogId": "anildash",
      "status": "ok",
      "postCount": 12,
      "lastFetched": "2026-03-22T03:34:03.195Z",
      "latencyMs": 623,
      "error": null
    },
    {
      "blogId": "spyglass",
      "status": "ok",
      "postCount": 15,
      "lastFetched": "2026-03-22T03:34:03.611Z",
      "latencyMs": 1029,
      "error": null
    },
    {
      "blogId": "honestbroker",
      "status": "ok",
      "postCount": 20,
      "lastFetched": "2026-03-22T03:34:03.086Z",
      "latencyMs": 432,
      "error": null
    },
    {
      "blogId": "wisdomofcrowds",
      "status": "ok",
      "postCount": 20,
      "lastFetched": "2026-03-22T03:34:03.230Z",
      "latencyMs": 545,
      "error": null
    },
    {
      "blogId": "bloodinthemachine",
      "status": "ok",
      "postCount": 20,
      "lastFetched": "2026-03-22T03:34:03.336Z",
      "latencyMs": 620,
      "error": null
    },
    {
      "blogId": "smallpotatoes",
      "status": "ok",
      "postCount": 20,
      "lastFetched": "2026-03-22T03:34:03.367Z",
      "latencyMs": 570,
      "error": null
    },
    {
      "blogId": "ageofinvention",
      "status": "ok",
      "postCount": 20,
      "lastFetched": "2026-03-22T03:34:03.387Z",
      "latencyMs": 463,
      "error": null
    },
    {
      "blogId": "optimallyirrational",
      "status": "ok",
      "postCount": 20,
      "lastFetched": "2026-03-22T03:34:03.571Z",
      "latencyMs": 485,
      "error": null
    },
    {
      "blogId": "conspicuouscognition",
      "status": "ok",
      "postCount": 20,
      "lastFetched": "2026-03-22T03:34:03.541Z",
      "latencyMs": 346,
      "error": null
    },
    {
      "blogId": "speakandregret",
      "status": "ok",
      "postCount": 20,
      "lastFetched": "2026-03-22T03:34:03.689Z",
      "latencyMs": 458,
      "error": null
    },
    {
      "blogId": "experimentalhistory",
      "status": "ok",
      "postCount": 20,
      "lastFetched": "2026-03-22T03:34:03.672Z",
      "latencyMs": 373,
      "error": null
    },
    {
      "blogId": "intrinsicperspective",
      "status": "ok",
      "postCount": 20,
      "lastFetched": "2026-03-22T03:34:03.741Z",
      "latencyMs": 405,
      "error": null
    },
    {
      "blogId": "everythingisbullshit",
      "status": "ok",
      "postCount": 20,
      "lastFetched": "2026-03-22T03:34:03.653Z",
      "latencyMs": 286,
      "error": null
    },
    {
      "blogId": "henrikkarlsson",
      "status": "ok",
      "postCount": 20,
      "lastFetched": "2026-03-22T03:34:03.714Z",
      "latencyMs": 327,
      "error": null
    },
    {
      "blogId": "aiascendant",
      "status": "ok",
      "postCount": 20,
      "lastFetched": "2026-03-22T03:34:03.681Z",
      "latencyMs": 235,
      "error": null
    },
    {
      "blogId": "danq",
      "status": "ok",
      "postCount": 25,
      "lastFetched": "2026-03-22T03:34:05.028Z",
      "latencyMs": 1487,
      "error": null
    },
    {
      "blogId": "mertbulan",
      "status": "ok",
      "postCount": 10,
      "lastFetched": "2026-03-22T03:34:03.697Z",
      "latencyMs": 126,
      "error": null
    },
    {
      "blogId": "tautvilas",
      "status": "ok",
      "postCount": 10,
      "lastFetched": "2026-03-22T03:34:03.929Z",
      "latencyMs": 318,
      "error": null
    },
    {
      "blogId": "oliverhartwich",
      "status": "ok",
      "postCount": 25,
      "lastFetched": "2026-03-22T03:34:03.747Z",
      "latencyMs": 94,
      "error": null
    },
    {
      "blogId": "miketech",
      "status": "ok",
      "postCount": 1,
      "lastFetched": "2026-03-22T03:34:03.769Z",
      "latencyMs": 97,
      "error": null
    },
    {
      "blogId": "platformer",
      "status": "ok",
      "postCount": 15,
      "lastFetched": "2026-03-22T03:34:03.830Z",
      "latencyMs": 149,
      "error": null
    },
    {
      "blogId": "scattershot",
      "status": "ok",
      "postCount": 25,
      "lastFetched": "2026-03-22T03:34:04.030Z",
      "latencyMs": 341,
      "error": null
    },
    {
      "blogId": "nadh",
      "status": "ok",
      "postCount": 18,
      "lastFetched": "2026-03-22T03:34:04.286Z",
      "latencyMs": 589,
      "error": null
    },
    {
      "blogId": "tessellatum",
      "status": "ok",
      "postCount": 10,
      "lastFetched": "2026-03-22T03:34:04.215Z",
      "latencyMs": 501,
      "error": null
    },
    {
      "blogId": "mostlyeconomics",
      "status": "ok",
      "postCount": 10,
      "lastFetched": "2026-03-22T03:34:03.833Z",
      "latencyMs": 92,
      "error": null
    },
    {
      "blogId": "matt",
      "status": "ok",
      "postCount": 25,
      "lastFetched": "2026-03-22T03:34:04.237Z",
      "latencyMs": 490,
      "error": null
    },
    {
      "blogId": "mrzepczynski",
      "status": "ok",
      "postCount": 25,
      "lastFetched": "2026-03-22T03:34:04.167Z",
      "latencyMs": 398,
      "error": null
    },
    {
      "blogId": "damodaran",
      "status": "ok",
      "postCount": 25,
      "lastFetched": "2026-03-22T03:34:04.021Z",
      "latencyMs": 190,
      "error": null
    },
    {
      "blogId": "ritholtz",
      "status": "ok",
      "postCount": 10,
      "lastFetched": "2026-03-22T03:34:04.094Z",
      "latencyMs": 261,
      "error": null
    },
    {
      "blogId": "danshapiro",
      "status": "ok",
      "postCount": 10,
      "lastFetched": "2026-03-22T03:34:05.615Z",
      "latencyMs": 1686,
      "error": null
    },
    {
      "blogId": "surfingcomplexity",
      "status": "ok",
      "postCount": 10,
      "lastFetched": "2026-03-22T03:34:04.113Z",
      "latencyMs": 92,
      "error": null
    },
    {
      "blogId": "jamesdrandall",
      "status": "ok",
      "postCount": 25,
      "lastFetched": "2026-03-22T03:34:04.779Z",
      "latencyMs": 749,
      "error": null
    },
    {
      "blogId": "scottsmitelli",
      "status": "ok",
      "postCount": 25,
      "lastFetched": "2026-03-22T03:34:04.225Z",
      "latencyMs": 130,
      "error": null
    },
    {
      "blogId": "karpathy",
      "status": "ok",
      "postCount": 10,
      "lastFetched": "2026-03-22T03:34:04.283Z",
      "latencyMs": 170,
      "error": null
    },
    {
      "blogId": "ivanturkovic",
      "status": "ok",
      "postCount": 10,
      "lastFetched": "2026-03-22T03:34:04.439Z",
      "latencyMs": 272,
      "error": null
    },
    {
      "blogId": "teendifferent",
      "status": "ok",
      "postCount": 8,
      "lastFetched": "2026-03-22T03:34:30.276Z",
      "latencyMs": 67,
      "error": null
    },
    {
      "blogId": "thezvi",
      "status": "ok",
      "postCount": 20,
      "lastFetched": "2026-03-22T03:34:30.460Z",
      "latencyMs": 250,
      "error": null
    },
    {
      "blogId": "hollisrobbins",
      "status": "ok",
      "postCount": 20,
      "lastFetched": "2026-03-22T03:34:30.365Z",
      "latencyMs": 153,
      "error": null
    },
    {
      "blogId": "freddiedeboer",
      "status": "ok",
      "postCount": 20,
      "lastFetched": "2026-03-22T03:34:30.344Z",
      "latencyMs": 131,
      "error": null
    },
    {
      "blogId": "onepercentrule",
      "status": "ok",
      "postCount": 20,
      "lastFetched": "2026-03-22T03:34:35.586Z",
      "latencyMs": 125,
      "error": null
    },
    {
      "blogId": "maxread",
      "status": "ok",
      "postCount": 20,
      "lastFetched": "2026-03-22T03:34:35.565Z",
      "latencyMs": 102,
      "error": null
    },
    {
      "blogId": "summerlightning",
      "status": "ok",
      "postCount": 20,
      "lastFetched": "2026-03-22T03:34:35.597Z",
      "latencyMs": 132,
      "error": null
    },
    {
      "blogId": "ghostsofelectricity",
      "status": "ok",
      "postCount": 11,
      "lastFetched": "2026-03-22T03:34:35.607Z",
      "latencyMs": 141,
      "error": null
    },
    {
      "blogId": "kneelingbus",
      "status": "ok",
      "postCount": 20,
      "lastFetched": "2026-03-22T03:34:40.681Z",
      "latencyMs": 73,
      "error": null
    },
    {
      "blogId": "thecuttingfloor",
      "status": "ok",
      "postCount": 20,
      "lastFetched": "2026-03-22T03:34:40.716Z",
      "latencyMs": 106,
      "error": null
    },
    {
      "blogId": "paulkrugman",
      "status": "ok",
      "postCount": 20,
      "lastFetched": "2026-03-22T03:34:40.694Z",
      "latencyMs": 82,
      "error": null
    },
    {
      "blogId": "arpitrage",
      "status": "ok",
      "postCount": 20,
      "lastFetched": "2026-03-22T03:34:40.769Z",
      "latencyMs": 156,
      "error": null
    },
    {
      "blogId": "kyla",
      "status": "ok",
      "postCount": 20,
      "lastFetched": "2026-03-22T03:34:45.897Z",
      "latencyMs": 127,
      "error": null
    },
    {
      "blogId": "larryswedroe",
      "status": "ok",
      "postCount": 20,
      "lastFetched": "2026-03-22T03:34:45.906Z",
      "latencyMs": 134,
      "error": null
    },
    {
      "blogId": "klementoninvesting",
      "status": "ok",
      "postCount": 20,
      "lastFetched": "2026-03-22T03:34:45.912Z",
      "latencyMs": 139,
      "error": null
    },
    {
      "blogId": "downtownjoshbrown",
      "status": "ok",
      "postCount": 3,
      "lastFetched": "2026-03-22T03:34:45.947Z",
      "latencyMs": 172,
      "error": null
    },
    {
      "blogId": "betterletter",
      "status": "ok",
      "postCount": 20,
      "lastFetched": "2026-03-22T03:34:51.124Z",
      "latencyMs": 177,
      "error": null
    },
    {
      "blogId": "overthefield",
      "status": "ok",
      "postCount": 20,
      "lastFetched": "2026-03-22T03:34:51.045Z",
      "latencyMs": 96,
      "error": null
    },
    {
      "blogId": "pilgrimsinthemachine",
      "status": "ok",
      "postCount": 20,
      "lastFetched": "2026-03-22T03:34:51.062Z",
      "latencyMs": 112,
      "error": null
    },
    {
      "blogId": "convivialsociety",
      "status": "ok",
      "postCount": 20,
      "lastFetched": "2026-03-22T03:34:51.033Z",
      "latencyMs": 82,
      "error": null
    },
    {
      "blogId": "stockviz",
      "status": "ok",
      "postCount": 20,
      "lastFetched": "2026-03-22T03:34:56.287Z",
      "latencyMs": 162,
      "error": null
    },
    {
      "blogId": "openquestions",
      "status": "ok",
      "postCount": 20,
      "lastFetched": "2026-03-22T03:34:56.224Z",
      "latencyMs": 98,
      "error": null
    },
    {
      "blogId": "wollenblog",
      "status": "ok",
      "postCount": 20,
      "lastFetched": "2026-03-22T03:34:56.237Z",
      "latencyMs": 109,
      "error": null
    },
    {
      "blogId": "koenfucius",
      "status": "ok",
      "postCount": 20,
      "lastFetched": "2026-03-22T03:34:56.263Z",
      "latencyMs": 134,
      "error": null
    },
    {
      "blogId": "benthamsbulldog",
      "status": "ok",
      "postCount": 20,
      "lastFetched": "2026-03-22T03:35:01.396Z",
      "latencyMs": 108,
      "error": null
    },
    {
      "blogId": "curtjaimungal",
      "status": "ok",
      "postCount": 20,
      "lastFetched": "2026-03-22T03:35:01.376Z",
      "latencyMs": 86,
      "error": null
    },
    {
      "blogId": "nicholasgruen",
      "status": "ok",
      "postCount": 20,
      "lastFetched": "2026-03-22T03:35:02.000Z",
      "latencyMs": 709,
      "error": null
    },
    {
      "blogId": "atmoio",
      "status": "ok",
      "postCount": 4,
      "lastFetched": "2026-03-22T03:35:01.382Z",
      "latencyMs": 90,
      "error": null
    },
    {
      "blogId": "pertinentobservations",
      "status": "ok",
      "postCount": 20,
      "lastFetched": "2026-03-22T03:35:07.094Z",
      "latencyMs": 93,
      "error": null
    },
    {
      "blogId": "nevermetascience",
      "status": "ok",
      "postCount": 20,
      "lastFetched": "2026-03-22T03:35:07.151Z",
      "latencyMs": 149,
      "error": null
    },
    {
      "blogId": "personalcanon",
      "status": "ok",
      "postCount": 20,
      "lastFetched": "2026-03-22T03:35:07.307Z",
      "latencyMs": 304,
      "error": null
    },
    {
      "blogId": "cosmographia",
      "status": "ok",
      "postCount": 20,
      "lastFetched": "2026-03-22T03:35:07.084Z",
      "latencyMs": 81,
      "error": null
    },
    {
      "blogId": "nadig",
      "status": "ok",
      "postCount": 20,
      "lastFetched": "2026-03-22T03:35:12.475Z",
      "latencyMs": 167,
      "error": null
    },
    {
      "blogId": "thechoiceengine",
      "status": "ok",
      "postCount": 9,
      "lastFetched": "2026-03-22T03:35:12.496Z",
      "latencyMs": 187,
      "error": null
    },
    {
      "blogId": "braddelong",
      "status": "ok",
      "postCount": 20,
      "lastFetched": "2026-03-22T03:35:12.422Z",
      "latencyMs": 113,
      "error": null
    },
    {
      "blogId": "branko",
      "status": "ok",
      "postCount": 20,
      "lastFetched": "2026-03-22T03:35:12.403Z",
      "latencyMs": 93,
      "error": null
    },
    {
      "blogId": "bignewsletter",
      "status": "ok",
      "postCount": 20,
      "lastFetched": "2026-03-22T03:35:17.625Z",
      "latencyMs": 128,
      "error": null
    },
    {
      "blogId": "economicforces",
      "status": "ok",
      "postCount": 20,
      "lastFetched": "2026-03-22T03:35:17.687Z",
      "latencyMs": 188,
      "error": null
    },
    {
      "blogId": "thebasecamp",
      "status": "ok",
      "postCount": 20,
      "lastFetched": "2026-03-22T03:35:17.602Z",
      "latencyMs": 102,
      "error": null
    },
    {
      "blogId": "worksonmymachine",
      "status": "ok",
      "postCount": 20,
      "lastFetched": "2026-03-22T03:35:17.710Z",
      "latencyMs": 209,
      "error": null
    },
    {
      "blogId": "cleareyedai",
      "status": "ok",
      "postCount": 20,
      "lastFetched": "2026-03-22T03:35:22.868Z",
      "latencyMs": 157,
      "error": null
    },
    {
      "blogId": "davidoks",
      "status": "ok",
      "postCount": 16,
      "lastFetched": "2026-03-22T03:35:22.831Z",
      "latencyMs": 119,
      "error": null
    },
    {
      "blogId": "robhenderson",
      "status": "ok",
      "postCount": 20,
      "lastFetched": "2026-03-22T03:35:22.816Z",
      "latencyMs": 103,
      "error": null
    },
    {
      "blogId": "andymasley",
      "status": "ok",
      "postCount": 20,
      "lastFetched": "2026-03-22T03:35:22.897Z",
      "latencyMs": 183,
      "error": null
    },
    {
      "blogId": "helentoner",
      "status": "ok",
      "postCount": 9,
      "lastFetched": "2026-03-22T03:35:28.002Z",
      "latencyMs": 104,
      "error": null
    },
    {
      "blogId": "persuasion",
      "status": "ok",
      "postCount": 20,
      "lastFetched": "2026-03-22T03:35:28.213Z",
      "latencyMs": 314,
      "error": null
    },
    {
      "blogId": "afterbabel",
      "status": "ok",
      "postCount": 20,
      "lastFetched": "2026-03-22T03:35:27.993Z",
      "latencyMs": 94,
      "error": null
    },
    {
      "blogId": "importai",
      "status": "ok",
      "postCount": 20,
      "lastFetched": "2026-03-22T03:35:28.028Z",
      "latencyMs": 128,
      "error": null
    },
    {
      "blogId": "byfire",
      "status": "ok",
      "postCount": 11,
      "lastFetched": "2026-03-22T03:35:33.306Z",
      "latencyMs": 92,
      "error": null
    },
    {
      "blogId": "investmentecosystem",
      "status": "ok",
      "postCount": 6,
      "lastFetched": "2026-03-22T03:35:33.293Z",
      "latencyMs": 78,
      "error": null
    },
    {
      "blogId": "weltinnenpolitik",
      "status": "ok",
      "postCount": 15,
      "lastFetched": "2026-03-22T03:35:33.344Z",
      "latencyMs": 127,
      "error": null
    },
    {
      "blogId": "protocolized",
      "status": "ok",
      "postCount": 20,
      "lastFetched": "2026-03-22T03:35:33.328Z",
      "latencyMs": 112,
      "error": null
    },
    {
      "blogId": "minutes",
      "status": "ok",
      "postCount": 20,
      "lastFetched": "2026-03-22T03:35:38.508Z",
      "latencyMs": 164,
      "error": null
    },
    {
      "blogId": "anticipatingtheunintended",
      "status": "ok",
      "postCount": 20,
      "lastFetched": "2026-03-22T03:35:38.473Z",
      "latencyMs": 128,
      "error": null
    }
  ],
  "summary": {
    "total": 142,
    "healthy": 141,
    "errors": 1
  }
}